mirrai/__init__.py
mirrai/api/__init__.py
mirrai/api/converters.py
mirrai/api/execution_adapter.py
mirrai/api/main.py
mirrai/api/models.py
mirrai/api/endpoints/__init__.py
mirrai/api/endpoints/agent.py
mirrai/api/endpoints/windows.py
mirrai/cli/__init__.py
mirrai/cli/cli.py
mirrai/cli/commands/__init__.py
mirrai/cli/commands/agent.py
mirrai/cli/commands/api.py
mirrai/cli/commands/capture.py
mirrai/cli/commands/window.py
mirrai/core/__init__.py
mirrai/core/capture.py
mirrai/core/constants.py
mirrai/core/logger.py
mirrai/core/agent/__init__.py
mirrai/core/agent/execution.py
mirrai/core/agent/models.py
mirrai/core/agent/output.py
mirrai/core/agent/tool_handler.py
mirrai/core/execution/__init__.py
mirrai/core/execution/exceptions.py
mirrai/core/execution/manager.py
mirrai/core/execution/models.py
mirrai/core/execution/events/__init__.py
mirrai/core/execution/events/emitter.py
mirrai/core/execution/events/types.py
mirrai/core/execution/storage/__init__.py
mirrai/core/execution/storage/base.py
mirrai/core/execution/storage/memory.py
mirrai/core/input_controller/__init__.py
mirrai/core/input_controller/base.py
mirrai/core/input_controller/factory.py
mirrai/core/input_controller/linux.py
mirrai/core/input_controller/macos.py
mirrai/core/input_controller/windows.py
mirrai/core/providers/__init__.py
mirrai/core/providers/anthropic.py
mirrai/core/providers/base.py
mirrai/core/providers/factory.py
mirrai/core/providers/openrouter.py
mirrai/core/utils/__init__.py
mirrai/core/utils/common.py
mirrai/core/utils/macos_permissions.py
mirrai/core/utils/patterns.py
mirrai/core/window_manager/__init__.py
mirrai/core/window_manager/base.py
mirrai/core/window_manager/factory.py
mirrai/core/window_manager/linux.py
mirrai/core/window_manager/linux_i3.py
mirrai/core/window_manager/macos.py
mirrai/core/window_manager/models.py
mirrai/core/window_manager/windows.py
mirrai-0.4.0.dist-info/METADATA
mirrai-0.4.0.dist-info/WHEEL
mirrai-0.4.0.dist-info/entry_points.txt
mirrai-0.4.0.dist-info/licenses/LICENSE
mirrai-0.4.0.dist-info/RECORD
