Metadata-Version: 2.4
Name: mirrai
Version: 0.4.0
Summary: A Multimodal AI agent for desktop automation via screenshots and tool use.
Project-URL: Homepage, https://pypi.org/project/mirrai/
Author-email: Justin Garofolo <justin@garofolo.net>
Maintainer-email: Justin Garofolo <justin@garofolo.net>
License: Apache-2.0
License-File: LICENSE
Keywords: agent,ai,automation,desktop
Classifier: Development Status :: 3 - Alpha
Classifier: Intended Audience :: Developers
Classifier: License :: OSI Approved :: Apache Software License
Classifier: Operating System :: MacOS :: MacOS X
Classifier: Operating System :: Microsoft :: Windows
Classifier: Operating System :: POSIX :: Linux
Classifier: Programming Language :: Python :: 3
Classifier: Programming Language :: Python :: 3.11
Classifier: Programming Language :: Python :: 3.12
Classifier: Topic :: Software Development :: Libraries :: Python Modules
Classifier: Topic :: Software Development :: Quality Assurance
Classifier: Topic :: System :: Monitoring
Classifier: Topic :: Utilities
Requires-Python: >=3.11
Requires-Dist: anthropic>=0.64.0
Requires-Dist: ewmh>=0.1.6; sys_platform == 'linux'
Requires-Dist: fastapi>=0.116.1
Requires-Dist: httpx>=0.25.0
Requires-Dist: mss>=9.0.0
Requires-Dist: numpy>=1.26.0
Requires-Dist: openai>=1.99.9
Requires-Dist: pillow>=11.3.0
Requires-Dist: psutil>=5.9.0
Requires-Dist: pyautogui>=0.9.54
Requires-Dist: pydantic>=2.11.7
Requires-Dist: pynput>=1.8.1; sys_platform == 'linux'
Requires-Dist: pyobjc-core>=10.0; sys_platform == 'darwin'
Requires-Dist: pyobjc-framework-applicationservices>=10.0; sys_platform == 'darwin'
Requires-Dist: pyobjc-framework-cocoa>=10.0; sys_platform == 'darwin'
Requires-Dist: pyobjc-framework-quartz>=10.0; sys_platform == 'darwin'
Requires-Dist: python-dotenv>=1.0.0
Requires-Dist: python-xlib>=0.33; sys_platform == 'linux'
Requires-Dist: pytweening>=1.2.0
Requires-Dist: pywin32>=311; sys_platform == 'win32'
Requires-Dist: rich>=14.1.0
Requires-Dist: typer>=0.16.0
Requires-Dist: uvicorn[standard]>=0.35.0
Provides-Extra: dev
Requires-Dist: basedpyright>=1.31.2; extra == 'dev'
Requires-Dist: black>=25.1.0; extra == 'dev'
Requires-Dist: build>=1.0.0; extra == 'dev'
Requires-Dist: hatch; extra == 'dev'
Requires-Dist: invoke>=2.2.0; extra == 'dev'
Requires-Dist: isort>=5.13.0; extra == 'dev'
Requires-Dist: twine>=6.0.0; extra == 'dev'
